dr_plotter/__init__.py
dr_plotter/artist_utils.py
dr_plotter/channel_metadata.py
dr_plotter/cli.py
dr_plotter/consts.py
dr_plotter/figure_manager.py
dr_plotter/legend_manager.py
dr_plotter/plot_presets.py
dr_plotter/style_applicator.py
dr_plotter/style_engine.py
dr_plotter/styling_utils.py
dr_plotter/theme.py
dr_plotter/types.py
dr_plotter/utils.py
dr_plotter/configs/__init__.py
dr_plotter/configs/cycle_config.py
dr_plotter/configs/faceting_config.py
dr_plotter/configs/grouping_config.py
dr_plotter/configs/layout_config.py
dr_plotter/configs/legend_config.py
dr_plotter/configs/plot_config.py
dr_plotter/configs/style_config.py
dr_plotter/faceting/__init__.py
dr_plotter/faceting/dimensional_utils.py
dr_plotter/faceting/faceting_core.py
dr_plotter/faceting/layout_utils.py
dr_plotter/faceting/style_coordination.py
dr_plotter/plotters/__init__.py
dr_plotter/plotters/bar.py
dr_plotter/plotters/base.py
dr_plotter/plotters/bump.py
dr_plotter/plotters/contour.py
dr_plotter/plotters/heatmap.py
dr_plotter/plotters/histogram.py
dr_plotter/plotters/line.py
dr_plotter/plotters/scatter.py
dr_plotter/plotters/violin.py
dr_plotter/scripting/__init__.py
dr_plotter/scripting/cli_framework.py
dr_plotter/scripting/comparison_utils.py
dr_plotter/scripting/config_schema.py
dr_plotter/scripting/plot_data.py
dr_plotter/scripting/plot_data_extractor.py
dr_plotter/scripting/unified_verification_engine.py
dr_plotter/scripting/utils.py
dr_plotter/scripting/verif_decorators.py
dr_plotter/scripting/verification_formatter.py
dr_plotter-0.1.2.dist-info/METADATA
dr_plotter-0.1.2.dist-info/WHEEL
dr_plotter-0.1.2.dist-info/entry_points.txt
dr_plotter-0.1.2.dist-info/RECORD
