Metadata-Version: 2.4
Name: dr_plotter
Version: 0.1.2
Summary: A general-purpose plotting library for creating publication-quality figures.
Author-email: Danielle Rothermel <danielle.rothermel@gmail.com>
Requires-Python: >=3.9
Requires-Dist: click>=8.0.0
Requires-Dist: matplotlib>=3.9.4
Requires-Dist: numpy>=2.0.2
Requires-Dist: pandas>=2.3.1
Requires-Dist: pyarrow>=21.0.0
Requires-Dist: pydantic>=2.11.7
Requires-Dist: pyyaml>=6.0.0
Requires-Dist: scikit-learn>=1.6.1
Requires-Dist: scipy>=1.13.1
Requires-Dist: seaborn>=0.13.2
